pyeconomics/__init__.py
pyeconomics/__version__.py
pyeconomics/api/__init__.py
pyeconomics/api/cache_manager.py
pyeconomics/api/fred_api.py
pyeconomics/api/fred_data.py
pyeconomics/data/__init__.py
pyeconomics/data/economic_indicators.py
pyeconomics/data/model_parameters.py
pyeconomics/models/__init__.py
pyeconomics/models/monetary_policy/__init__.py
pyeconomics/models/monetary_policy/balanced_approach_rule.py
pyeconomics/models/monetary_policy/first_difference_rule.py
pyeconomics/models/monetary_policy/monetary_policy_rules.py
pyeconomics/models/monetary_policy/taylor_rule.py
pyeconomics/utils/__init__.py
pyeconomics/utils/bar_utils.py
pyeconomics/utils/fdr_utils.py
pyeconomics/utils/tr_utils.py
tests/__init__.py
tests/conftest.py
tests/test_balanced_approach_rule.py
tests/test_bar_utils.py
tests/test_cache_manager.py
tests/test_fdr_utils.py
tests/test_first_difference_rule.py
tests/test_fred_api.py
tests/test_fred_data.py
tests/test_monetary_policy_rules.py
tests/test_taylor_rule.py
tests/test_tr_utils.py
pyeconomics-0.2.5.dist-info/LICENSE
pyeconomics-0.2.5.dist-info/METADATA
pyeconomics-0.2.5.dist-info/WHEEL
pyeconomics-0.2.5.dist-info/top_level.txt
pyeconomics-0.2.5.dist-info/RECORD
