Metadata-Version: 2.1
Name: pyeconomics
Version: 0.2.5
Summary: A library for economic and financial analysis
Home-page: https://github.com/nathanramoscfa/pyeconomics
Author: Nathan Ramos, CFA
Author-email: nathan.ramos.github@gmail.com
Project-URL: Bug Reports, https://github.com/nathanramoscfa/pyeconomics/issues
Project-URL: Source, https://github.com/nathanramoscfa/pyeconomics
Classifier: Development Status :: 3 - Alpha
Classifier: Intended Audience :: Developers
Classifier: Intended Audience :: Financial and Insurance Industry
Classifier: Programming Language :: Python :: 3.11
Classifier: Programming Language :: Python :: 3.12
Classifier: License :: OSI Approved :: MIT License
Classifier: Operating System :: OS Independent
Classifier: Topic :: Office/Business :: Financial
Classifier: Topic :: Office/Business :: Financial :: Investment
Requires-Python: >=3.11, <3.13
License-File: LICENSE
Requires-Dist: fredapi ~=0.5.1
Requires-Dist: jupyterlab ~=4.1.8
Requires-Dist: keyring ~=25.2.0
Requires-Dist: matplotlib ~=3.8.4
Requires-Dist: openai ~=1.30.1
Requires-Dist: pandas ~=2.2.2
Requires-Dist: pytest ~=8.2.0
Requires-Dist: setuptools ~=68.2.2
Requires-Dist: sphinx ~=7.3.7
Requires-Dist: sphinx-rtd-theme ~=2.0.0
